<?xml version="1.0" encoding="UTF-8"?><record_update table="catalog_ui_policy_action">
    <catalog_ui_policy_action action="DELETE">
        <catalog_item display_value="ITCM Support">bd0082d41be409d01cf976ae034bcb20</catalog_item>
        <catalog_variable>IO:8b88eaa81be80dd01cf976ae034bcb4e</catalog_variable>
        <cleared>true</cleared>
        <disabled>ignore</disabled>
        <field/>
        <mandatory>true</mandatory>
        <order>100</order>
        <sys_class_name>catalog_ui_policy_action</sys_class_name>
        <sys_created_by>SA\ACSIMOE</sys_created_by>
        <sys_created_on>2022-01-27 14:08:26</sys_created_on>
        <sys_id>4d8f3c3d1b9181144a61ebd22a4bcb66</sys_id>
        <sys_mod_count>2</sys_mod_count>
        <sys_name>field_to_be_updates</sys_name>
        <sys_package display_value="ITCM Support" source="x_iem_itcm_support">f01ed1941b6cc5d01cf976ae034bcb86</sys_package>
        <sys_policy/>
        <sys_scope display_value="ITCM Support">f01ed1941b6cc5d01cf976ae034bcb86</sys_scope>
        <sys_update_name>catalog_ui_policy_action_4d8f3c3d1b9181144a61ebd22a4bcb66</sys_update_name>
        <sys_updated_by>system</sys_updated_by>
        <sys_updated_on>2022-01-27 14:14:11</sys_updated_on>
        <table/>
        <ui_policy display_value="Make 'field_to_be_updates' mandatory &amp; visible depending on 'choose_module_mr_rh_gra' &amp; 'what_is_this_request_for'">c18f3c3d1b9181144a61ebd22a4bcb63</ui_policy>
        <variable>field_to_be_updates</variable>
        <variable_set/>
        <visible>true</visible>
    </catalog_ui_policy_action>
    <sys_update_version action="INSERT_OR_UPDATE">
        <action>DELETE</action>
        <application display_value="ITCM Support">f01ed1941b6cc5d01cf976ae034bcb86</application>
        <file_path/>
        <instance_id>c383490ddb92b700387021c405961992</instance_id>
        <instance_name>emcitizendev</instance_name>
        <name>catalog_ui_policy_action_4d8f3c3d1b9181144a61ebd22a4bcb66</name>
        <payload><![CDATA[<?xml version="1.0" encoding="UTF-8"?><record_update table="catalog_ui_policy_action"><catalog_ui_policy_action action="INSERT_OR_UPDATE"><catalog_item display_value="ITCM Support">bd0082d41be409d01cf976ae034bcb20</catalog_item><catalog_variable>IO:8b88eaa81be80dd01cf976ae034bcb4e</catalog_variable><cleared>true</cleared><disabled>ignore</disabled><field/><mandatory>true</mandatory><order>100</order><sys_class_name>catalog_ui_policy_action</sys_class_name><sys_created_by>SA\ACSIMOE</sys_created_by><sys_created_on>2022-01-27 14:08:26</sys_created_on><sys_id>4d8f3c3d1b9181144a61ebd22a4bcb66</sys_id><sys_mod_count>2</sys_mod_count><sys_name>field_to_be_updates</sys_name><sys_package display_value="ITCM Support" source="x_iem_itcm_support">f01ed1941b6cc5d01cf976ae034bcb86</sys_package><sys_policy/><sys_scope display_value="ITCM Support">f01ed1941b6cc5d01cf976ae034bcb86</sys_scope><sys_update_name>catalog_ui_policy_action_4d8f3c3d1b9181144a61ebd22a4bcb66</sys_update_name><sys_updated_by>system</sys_updated_by><sys_updated_on>2022-01-27 14:14:11</sys_updated_on><table/><ui_policy display_value="Make 'field_to_be_updates' mandatory &amp; visible depending on 'choose_module_mr_rh_gra' &amp; 'what_is_this_request_for'">c18f3c3d1b9181144a61ebd22a4bcb63</ui_policy><variable>field_to_be_updates</variable><variable_set/><visible>true</visible></catalog_ui_policy_action></record_update>]]></payload>
        <payload_hash>-1779632831</payload_hash>
        <record_name>field_to_be_updates</record_name>
        <reverted_from/>
        <source>dba221541bacc5d01cf976ae034bcb35</source>
        <source_table>sys_update_set</source_table>
        <state>previous</state>
        <sys_created_by>system</sys_created_by>
        <sys_created_on>2022-01-27 14:14:11</sys_created_on>
        <sys_id>95d0c9311bd181144a61ebd22a4bcbf8</sys_id>
        <sys_mod_count>0</sys_mod_count>
        <sys_recorded_at>17e9be2fc7d0000001</sys_recorded_at>
        <sys_updated_by>system</sys_updated_by>
        <sys_updated_on>2022-01-27 14:14:11</sys_updated_on>
        <type>Catalog UI Policy Action</type>
        <update_guid>99d0c931add18114754dd9ba271c47f7</update_guid>
        <update_guid_history>99d0c931add18114754dd9ba271c47f7:-1779632831,c58f3c3d3f918114c297471a5c96416e:-1338747275,858f3c3d76918114cd6da5b4ce00a469:-1779632831</update_guid_history>
    </sys_update_version>
    <sys_metadata_delete action="INSERT_OR_UPDATE">
        <sys_audit_delete display_value="field_to_be_updates">7503493d1bd989901cf976ae034bcbc2</sys_audit_delete>
        <sys_class_name>sys_metadata_delete</sys_class_name>
        <sys_created_by>system</sys_created_by>
        <sys_created_on>2022-01-27 14:23:46</sys_created_on>
        <sys_db_object display_value="" name="catalog_ui_policy_action">catalog_ui_policy_action</sys_db_object>
        <sys_id>8fdf34ea687b4063991d96ca90e42849</sys_id>
        <sys_metadata>4d8f3c3d1b9181144a61ebd22a4bcb66</sys_metadata>
        <sys_mod_count>0</sys_mod_count>
        <sys_name>field_to_be_updates</sys_name>
        <sys_package display_value="ITCM Support" source="x_iem_itcm_support">f01ed1941b6cc5d01cf976ae034bcb86</sys_package>
        <sys_parent/>
        <sys_policy/>
        <sys_scope display_value="ITCM Support">f01ed1941b6cc5d01cf976ae034bcb86</sys_scope>
        <sys_scope_delete display_value="">3388bca3ce7647448fdcc1d13ce674f1</sys_scope_delete>
        <sys_update_name>catalog_ui_policy_action_4d8f3c3d1b9181144a61ebd22a4bcb66</sys_update_name>
        <sys_update_version display_value="catalog_ui_policy_action_4d8f3c3d1b9181144a61ebd22a4bcb66">95d0c9311bd181144a61ebd22a4bcbf8</sys_update_version>
        <sys_updated_by>system</sys_updated_by>
        <sys_updated_on>2022-01-27 14:23:46</sys_updated_on>
    </sys_metadata_delete>
</record_update>
